sigma/backends/secops/__init__.py
sigma/backends/secops/secops.py
sigma/pipelines/secops/__init__.py
sigma/pipelines/secops/errors.py
sigma/pipelines/secops/mappings.py
sigma/pipelines/secops/postprocessing.py
sigma/pipelines/secops/secops.py
sigma/pipelines/secops/transformations.py
sigma/pipelines/secops/udm_field_schema.json
sigma/pipelines/secops/utils.py
sigma/pipelines/secops/validators.py
sigma/pipelines/secops/yara_l.py
pysigma_backend_secops-0.1.4.dist-info/LICENSE
pysigma_backend_secops-0.1.4.dist-info/METADATA
pysigma_backend_secops-0.1.4.dist-info/WHEEL
pysigma_backend_secops-0.1.4.dist-info/RECORD
